hiveviewer/__init__.py
hiveviewer/dataloader/__init__.py
hiveviewer/dataloader/base.py
hiveviewer/dataloader/load_csv.py
hiveviewer/dataloader/load_excel.py
hiveviewer/evaluation/__init__.py
hiveviewer/evaluation/calculator.py
hiveviewer/optimization/__init__.py
hiveviewer/optimization/base.py
hiveviewer/optimization/multiple_objective.py
hiveviewer/sampling/__init__.py
hiveviewer/sampling/base.py
hiveviewer/sampling/frequency_sampler.py
hiveviewer/sampling/gini_sampler.py
hiveviewer/visualization/__init__.py
hiveviewer/visualization/lorenz_curve.py
hiveviewer/visualization/plot_trisurf.py
hiveviewer/visualization/profolio_curve.py
hiveviewer/visualization/venn2.py
hiveviewer/visualization/venn3.py
hiveviewer/visualization/venn_base.py
hiveviewer-0.2.11.dist-info/LICENSE
hiveviewer-0.2.11.dist-info/METADATA
hiveviewer-0.2.11.dist-info/WHEEL
hiveviewer-0.2.11.dist-info/top_level.txt
hiveviewer-0.2.11.dist-info/RECORD
