Metadata-Version: 2.1
Name: hiveviewer
Version: 0.2.11
Summary: Offers a toolset for comprehensive, multi-faceted analysis of data exported from Hive, accompanied by powerful data visualization capabilities.
Home-page: https://github.com/yinsn/hiveviewer
Author: Yin Cheng
Author-email: yin.sjtu@gmail.com
Requires-Python: >=3.6
License-File: LICENSE
Requires-Dist: imageio
Requires-Dist: matplotlib-venn
Requires-Dist: matplotlib
Requires-Dist: numpy
Requires-Dist: openpyxl
Requires-Dist: optuna
Requires-Dist: pandas
Requires-Dist: scikit-learn
Requires-Dist: tqdm
